graia/application/__init__.py
graia/application/context.py
graia/application/entities.py
graia/application/entry.py
graia/application/event/__init__.py
graia/application/event/dispatcher.py
graia/application/event/lifecycle.py
graia/application/event/messages.py
graia/application/event/mirai.py
graia/application/event/network.py
graia/application/exceptions.py
graia/application/friend.py
graia/application/group.py
graia/application/interrupts.py
graia/application/logger.py
graia/application/message/__init__.py
graia/application/message/chain.py
graia/application/message/elements/__init__.py
graia/application/message/elements/external.py
graia/application/message/elements/internal.py
graia/application/message/parser/__init__.py
graia/application/message/parser/kanata.py
graia/application/message/parser/literature.py
graia/application/message/parser/pack.py
graia/application/message/parser/pattern.py
graia/application/message/parser/signature.py
graia/application/session.py
graia/application/test/__init__.py
graia/application/test/request_tracing.py
graia/application/utilles.py
graia_application_mirai-0.20.1.dist-info/LICENSE
graia_application_mirai-0.20.1.dist-info/WHEEL
graia_application_mirai-0.20.1.dist-info/METADATA
graia_application_mirai-0.20.1.dist-info/RECORD
