Metadata-Version: 2.1
Name: graia-application-mirai
Version: 0.20.1
Summary: 
License: AGPL-3.0
Author: GreyElaina
Author-email: GreyElaina@outlook.com
Requires-Python: >=3.6,<4.0
Classifier: License :: OSI Approved :: GNU Affero General Public License v3
Classifier: Programming Language :: Python :: 3
Classifier: Programming Language :: Python :: 3.6
Classifier: Programming Language :: Python :: 3.7
Classifier: Programming Language :: Python :: 3.8
Classifier: Programming Language :: Python :: 3.9
Requires-Dist: aiohttp (>=3.6.2,<4.0.0)
Requires-Dist: contextvars (>=2.4,<3.0); python_version < "3.7"
Requires-Dist: graia-broadcast (>=0.11.0,<0.12.0)
Requires-Dist: pydantic (>=1.8.2,<2.0.0)
Requires-Dist: regex (>=2020.7.14,<2021.0.0)
Requires-Dist: yarl (>=1.4.2,<2.0.0)
